MANIFEST.in
_utf7.c
_utf7.pyx
setup.py
utf7.c
utf7.h
utf7.py
utf7.egg-info/PKG-INFO
utf7.egg-info/SOURCES.txt
utf7.egg-info/dependency_links.txt
utf7.egg-info/top_level.txt