Metadata-Version: 1.1
Name: utf7
Version: 0.9.3
Summary: UTF-7 encoded unsigned integer
Home-page: https://github.com/sublee/utf7
Author: Heungsub Lee
Author-email: sub@subl.ee
License: BSD
Download-URL: http://github.com/sublee/utf7/zipball/master#egg=utf7-dev
Platform: a
Platform: n
Platform: y
Classifier: Development Status :: 4 - Beta
Classifier: Intended Audience :: Developers
Classifier: License :: OSI Approved :: BSD License
Classifier: Operating System :: OS Independent
Classifier: Programming Language :: Python
Classifier: Programming Language :: Python :: 2
Classifier: Programming Language :: Python :: 2.6
Classifier: Programming Language :: Python :: 2.7
Classifier: Programming Language :: Python :: 3
Classifier: Programming Language :: Python :: 3.1
Classifier: Programming Language :: Python :: 3.2
Classifier: Programming Language :: Python :: 3.3
Classifier: Programming Language :: Python :: Implementation :: CPython
Classifier: Programming Language :: Python :: Implementation :: PyPy
